{
  "entity": "ACT New Zealand",
  "properties": {
    "country": "New Zealand",
    "ideology": "Libertarianism",
    "founded": "1996",
    "leader": "David Seymour",
    "colour": "Blue",
    "representation": "Parliament",
    "focus": "Economic freedom",
    "position_on_spectrum": "Right-wing",
    "official_website": "act.org.nz",
    "type": "Political party"
  },
  "relationship": [
    {
      "political_party_of": "New Zealand"
    },
    {
      "member_of": "New Zealand Parliament"
    },
    {
      "leader_of": "David Seymour"
    },
    {
      "ideology": "Liberalism"
    },
    {
      "founded_by": "Rodney Hide"
    },
    {
      "successor_of": "New Zealand National Party"
    },
    {
      "influenced_by": "Act Party (Australia)"
    },
    {
      "policy_position_on": "Economic Liberalism"
    },
    {
      "election_result_of": "New Zealand general election"
    },
    {
      "has_member": "Jamie Whyte"
    }
  ]
}