{
  "entity": "Canada",
  "properties": {
    "capital": "Ottawa",
    "official_languages": "English, French",
    "population": "38,250,000 (2023)",
    "area": "9,984,670 km²",
    "currency": "Canadian Dollar",
    "continent": "North America",
    "government_type": "Parliamentary democracy",
    "national_symbol": "Maple Leaf",
    "founding_date": "1867",
    "type": "Country"
  },
  "relationship": [
    {
      "located_in": "North America"
    },
    {
      "part_of": "United Nations"
    },
    {
      "member_of": "G7"
    },
    {
      "has_capital": "Ottawa"
    },
    {
      "borders": "United States"
    },
    {
      "has_official_language": "English language"
    },
    {
      "has_official_language": "French language"
    },
    {
      "influenced_by": "British Empire"
    },
    {
      "has_national_symbol": "Maple leaf"
    },
    {
      "has_head_of_state": "Monarch of Canada"
    }
  ]
}