{
  "entity": "Cultural Diversity",
  "properties": {
    "definition": "Variety of cultures",
    "synonym": "Multiculturalism",
    "scope": "Human societies",
    "aspects": "Language, beliefs, customs",
    "importance": "Social cohesion, innovation",
    "challenges": "Discrimination, prejudice",
    "benefits": "Enriched perspectives, creativity",
    "measurement": "Indices, surveys",
    "related_concept": "Intercultural communication",
    "impact_on": "Globalization",
    "type": "Concept"
  },
  "relationship": [
    {
      "instance_of": "Social_concept"
    },
    {
      "related_to": "Globalization"
    },
    {
      "causes": "Intercultural_communication"
    },
    {
      "results_in": "Cultural_exchange"
    },
    {
      "influences": "Identity_formation"
    },
    {
      "impacts": "Social_justice"
    },
    {
      "requires": "Tolerance"
    },
    {
      "promotes": "Empathy"
    },
    {
      "challenges": "Ethnocentrism"
    },
    {
      "manifests_in": "Multiculturalism"
    }
  ]
}