{
  "entity": "Falcon  Marvel Comics ",
  "properties": {
    "publisher": "Marvel Comics",
    "first_appearance": "Captain America #117",
    "creator": "Steve Englehart & Steve Ditko",
    "alter_ego": "Sam Wilson",
    "occupation": "Former U.S. Paratrooper, Vigilante",
    "powers": "Flight, Enhanced Strength, Combat Skills",
    "base_of_operations": "New York City",
    "affiliation": "Avengers",
    "species": "Human",
    "type": "Superhero"
  },
  "relationship": [
    {
      "instance_of": "fictional_character"
    },
    {
      "publisher": "Marvel Comics"
    },
    {
      "creator": "Stan Lee"
    },
    {
      "artist": "Gene Colan"
    },
    {
      "member_of": "Guardians of the Galaxy"
    },
    {
      "appears_in": "Captain Marvel (2006 series)"
    },
    {
      "affiliation": "Avengers"
    },
    {
      "has_power": "flight"
    },
    {
      "has_ability": "energy projection"
    },
    {
      "depicted_in": "Captain Marvel (film)"
    }
  ]
}