{
  "entity": "Ictinus",
  "properties": {
    "birth_date": "5th century BC (approx.)",
    "death_date": "4th century BC (approx.)",
    "nationality": "Ancient Greek",
    "field": "Architecture",
    "known_for": "Parthenon design",
    "worked_with": "Callicrates",
    "period": "Classical Greece",
    "location": "Athens",
    "style": "Classical Greek architecture",
    "type": "Architect"
  },
  "relationship": [
    {
      "architect": "Phidias"
    },
    {
      "located_in": "Athens"
    },
    {
      "part_of": "Acropolis"
    },
    {
      "architectural_style": "Doric"
    },
    {
      "used_for": "Temple"
    },
    {
      "dedicated_to": "Athena"
    },
    {
      "material": "Pentelic_marble"
    },
    {
      "influenced": "Parthenon"
    },
    {
      "historical_period": "Classical_Greece"
    },
    {
      "design_principle": "Harmony"
    }
  ]
}