{
  "entity": "Jetstar",
  "properties": {
    "hq_location": "Melbourne",
    "country": "Australia",
    "iata_code": "JQ",
    "icao_code": "LJ",
    "foundation_date": "2001",
    "parent_company": "Qantas",
    "fleet_size": "133",
    "hub_airport": "Melbourne Airport",
    "service_model": "Low-cost carrier",
    "type": "Airline"
  },
  "relationship": [
    {
      "instance_of": "airline"
    },
    {
      "parent_organization": "Qantas Airways"
    },
    {
      "headquarters_location": "Melbourne"
    },
    {
      "subsidiary_of": "Qantas Airways"
    },
    {
      "service_area": "Asia-Pacific"
    },
    {
      "country_of_origin": "Australia"
    },
    {
      "industry": "aviation"
    },
    {
      "has_product": "passenger transport"
    },
    {
      "employee_count": "3900"
    },
    {
      "founded_by": "Qantas Airways"
    }
  ]
}