{
  "entity": "Ngāpuhi",
  "properties": {
    "iwi_type": "Māori iwi",
    "location": "Northland, New Zealand",
    "population": "~40,000",
    "tribal_ancestor": "Kurahaupo",
    "rohe": "Te Tai o Aumaroa",
    "language": "Te Reo Māori",
    "traditional_occupation": "Fisheries, agriculture",
    "significant_figure": "Hone Heke",
    "treaty_signatory": "Numerous",
    "economic_activity": "Tourism, agriculture, forestry",
    "type": "Iwi"
  },
  "relationship": [
    {
      "instance_of": "ethnic_group"
    },
    {
      "located_in": "New Zealand"
    },
    {
      "part_of": "Māori_people"
    },
    {
      "has_traditional_territory": "Northland_Region"
    },
    {
      "ancestor_of": "Tāwhiao"
    },
    {
      "related_to": "Treaty_of_Waitangi"
    },
    {
      "has_leader": "Hone_Heke"
    },
    {
      "has_language": "Te_Reo_Māori"
    },
    {
      "has_cultural_artifact": "Pātaka"
    },
    {
      "subclass_of": "Māori_iwi"
    }
  ]
}