{
  "entity": "Openness",
  "properties": {
    "part_of": "Big Five personality traits",
    "description": "Trust, curiosity, imagination",
    "opposite_trait": "Closedness",
    "measurement_scale": "Likert scale",
    "related_to": "Intellect",
    "facet_includes": "Values",
    "type": "Personality trait"
  },
  "relationship": [
    {
      "instance_of": "Quality"
    },
    {
      "related_to": "Privacy"
    },
    {
      "related_to": "Transparency"
    },
    {
      "characteristic_of": "Communication"
    },
    {
      "characteristic_of": "Government"
    },
    {
      "related_to": "Trust"
    },
    {
      "related_to": "Honesty"
    },
    {
      "related_to": "Accountability"
    },
    {
      "related_to": "Collaboration"
    },
    {
      "related_to": "Inclusivity"
    }
  ]
}