{
  "entity": "Romanesque Architecture",
  "properties": {
    "time_period": "1000-1200 AD",
    "origin": "Europe",
    "style": "Architectural",
    "predecessor": "Carolingian Architecture",
    "successor": "Gothic Architecture",
    "characteristic_feature": "Rounded Arches",
    "building_materials": "Stone",
    "common_building_types": "Churches, Castles, Monasteries",
    "decoration": "Sculptural Ornamentation",
    "geographic_spread": "Western, Central, Eastern Europe",
    "type": "ArchitecturalStyle"
  },
  "relationship": [
    {
      "influenced": "Byzantine Architecture"
    },
    {
      "influenced_by": "Carolingian Architecture"
    },
    {
      "located_in": "Europe"
    },
    {
      "part_of": "Medieval Architecture"
    },
    {
      "created_by": "Romanesque Builders"
    },
    {
      "has_style": "Romanesque Sculpture"
    },
    {
      "has_feature": "Round Arch"
    },
    {
      "has_feature": "Barrel Vault"
    },
    {
      "used_for": "Religious Buildings"
    },
    {
      "influenced": "Gothic Architecture"
    }
  ]
}