{
  "entity": "Textile Industry",
  "properties": {
    "industry_type": "Manufacturing",
    "sector": "Secondary Sector",
    "global_value": "~$1.4 trillion (2021)",
    "major_inputs": "Raw fibers, dyes, chemicals",
    "key_processes": "Spinning, weaving, knitting, dyeing",
    "end_products": "Clothing, home furnishings, industrial textiles",
    "employment": "60 million+ globally",
    "environmental_impact": "Significant (water, chemicals)",
    "historical_origin": "Ancient civilizations",
    "modern_focus": "Sustainability, automation",
    "type": "Industry"
  },
  "relationship": [
    {
      "industry": "Manufacturing"
    },
    {
      "part_of": "Economy"
    },
    {
      "produces": "Clothing"
    },
    {
      "uses": "Cotton"
    },
    {
      "uses": "Polyester"
    },
    {
      "employs": "Labor"
    },
    {
      "regulated_by": "Government"
    },
    {
      "impacts": "Environment"
    },
    {
      "provides_input_to": "Fashion Industry"
    },
    {
      "related_to": "Supply Chain"
    }
  ]
}